[
  {
    "cardId": 4,
    "masterRank": 1,
    "resourceBoxId": 1
  },
  {
    "cardId": 4,
    "masterRank": 3,
    "resourceBoxId": 2
  },
  {
    "cardId": 4,
    "masterRank": 5,
    "resourceBoxId": 3
  },
  {
    "cardId": 88,
    "masterRank": 1,
    "resourceBoxId": 4
  },
  {
    "cardId": 88,
    "masterRank": 3,
    "resourceBoxId": 5
  },
  {
    "cardId": 88,
    "masterRank": 5,
    "resourceBoxId": 6
  },
  {
    "cardId": 92,
    "masterRank": 1,
    "resourceBoxId": 7
  },
  {
    "cardId": 92,
    "masterRank": 3,
    "resourceBoxId": 8
  },
  {
    "cardId": 92,
    "masterRank": 5,
    "resourceBoxId": 9
  },
  {
    "cardId": 96,
    "masterRank": 1,
    "resourceBoxId": 10
  },
  {
    "cardId": 96,
    "masterRank": 3,
    "resourceBoxId": 11
  },
  {
    "cardId": 96,
    "masterRank": 5,
    "resourceBoxId": 12
  },
  {
    "cardId": 109,
    "masterRank": 1,
    "resourceBoxId": 13
  },
  {
    "cardId": 109,
    "masterRank": 3,
    "resourceBoxId": 14
  },
  {
    "cardId": 109,
    "masterRank": 5,
    "resourceBoxId": 15
  },
  {
    "cardId": 110,
    "masterRank": 1,
    "resourceBoxId": 16
  },
  {
    "cardId": 110,
    "masterRank": 3,
    "resourceBoxId": 17
  },
  {
    "cardId": 110,
    "masterRank": 5,
    "resourceBoxId": 18
  },
  {
    "cardId": 114,
    "masterRank": 1,
    "resourceBoxId": 19
  },
  {
    "cardId": 114,
    "masterRank": 3,
    "resourceBoxId": 20
  },
  {
    "cardId": 114,
    "masterRank": 5,
    "resourceBoxId": 21
  },
  {
    "cardId": 115,
    "masterRank": 1,
    "resourceBoxId": 22
  },
  {
    "cardId": 115,
    "masterRank": 3,
    "resourceBoxId": 23
  },
  {
    "cardId": 115,
    "masterRank": 5,
    "resourceBoxId": 24
  },
  {
    "cardId": 119,
    "masterRank": 1,
    "resourceBoxId": 25
  },
  {
    "cardId": 119,
    "masterRank": 3,
    "resourceBoxId": 26
  },
  {
    "cardId": 119,
    "masterRank": 5,
    "resourceBoxId": 27
  },
  {
    "cardId": 120,
    "masterRank": 1,
    "resourceBoxId": 28
  },
  {
    "cardId": 120,
    "masterRank": 3,
    "resourceBoxId": 29
  },
  {
    "cardId": 120,
    "masterRank": 5,
    "resourceBoxId": 30
  },
  {
    "cardId": 124,
    "masterRank": 1,
    "resourceBoxId": 31
  },
  {
    "cardId": 124,
    "masterRank": 3,
    "resourceBoxId": 32
  },
  {
    "cardId": 124,
    "masterRank": 5,
    "resourceBoxId": 33
  },
  {
    "cardId": 125,
    "masterRank": 1,
    "resourceBoxId": 34
  },
  {
    "cardId": 125,
    "masterRank": 3,
    "resourceBoxId": 35
  },
  {
    "cardId": 125,
    "masterRank": 5,
    "resourceBoxId": 36
  },
  {
    "cardId": 129,
    "masterRank": 1,
    "resourceBoxId": 37
  },
  {
    "cardId": 129,
    "masterRank": 3,
    "resourceBoxId": 38
  },
  {
    "cardId": 129,
    "masterRank": 5,
    "resourceBoxId": 39
  },
  {
    "cardId": 130,
    "masterRank": 1,
    "resourceBoxId": 40
  },
  {
    "cardId": 130,
    "masterRank": 3,
    "resourceBoxId": 41
  },
  {
    "cardId": 130,
    "masterRank": 5,
    "resourceBoxId": 42
  },
  {
    "cardId": 134,
    "masterRank": 1,
    "resourceBoxId": 43
  },
  {
    "cardId": 134,
    "masterRank": 3,
    "resourceBoxId": 44
  },
  {
    "cardId": 134,
    "masterRank": 5,
    "resourceBoxId": 45
  },
  {
    "cardId": 135,
    "masterRank": 1,
    "resourceBoxId": 46
  },
  {
    "cardId": 135,
    "masterRank": 3,
    "resourceBoxId": 47
  },
  {
    "cardId": 135,
    "masterRank": 5,
    "resourceBoxId": 48
  },
  {
    "cardId": 139,
    "masterRank": 1,
    "resourceBoxId": 49
  },
  {
    "cardId": 139,
    "masterRank": 3,
    "resourceBoxId": 50
  },
  {
    "cardId": 139,
    "masterRank": 5,
    "resourceBoxId": 51
  },
  {
    "cardId": 140,
    "masterRank": 1,
    "resourceBoxId": 52
  },
  {
    "cardId": 140,
    "masterRank": 3,
    "resourceBoxId": 53
  },
  {
    "cardId": 140,
    "masterRank": 5,
    "resourceBoxId": 54
  },
  {
    "cardId": 144,
    "masterRank": 1,
    "resourceBoxId": 55
  },
  {
    "cardId": 144,
    "masterRank": 3,
    "resourceBoxId": 56
  },
  {
    "cardId": 144,
    "masterRank": 5,
    "resourceBoxId": 57
  },
  {
    "cardId": 145,
    "masterRank": 1,
    "resourceBoxId": 58
  },
  {
    "cardId": 145,
    "masterRank": 3,
    "resourceBoxId": 59
  },
  {
    "cardId": 145,
    "masterRank": 5,
    "resourceBoxId": 60
  },
  {
    "cardId": 149,
    "masterRank": 1,
    "resourceBoxId": 61
  },
  {
    "cardId": 149,
    "masterRank": 3,
    "resourceBoxId": 62
  },
  {
    "cardId": 149,
    "masterRank": 5,
    "resourceBoxId": 63
  },
  {
    "cardId": 150,
    "masterRank": 1,
    "resourceBoxId": 64
  },
  {
    "cardId": 150,
    "masterRank": 3,
    "resourceBoxId": 65
  },
  {
    "cardId": 150,
    "masterRank": 5,
    "resourceBoxId": 66
  },
  {
    "cardId": 155,
    "masterRank": 1,
    "resourceBoxId": 67
  },
  {
    "cardId": 155,
    "masterRank": 3,
    "resourceBoxId": 68
  },
  {
    "cardId": 155,
    "masterRank": 5,
    "resourceBoxId": 69
  },
  {
    "cardId": 156,
    "masterRank": 1,
    "resourceBoxId": 70
  },
  {
    "cardId": 156,
    "masterRank": 3,
    "resourceBoxId": 71
  },
  {
    "cardId": 156,
    "masterRank": 5,
    "resourceBoxId": 72
  },
  {
    "cardId": 160,
    "masterRank": 1,
    "resourceBoxId": 73
  },
  {
    "cardId": 160,
    "masterRank": 3,
    "resourceBoxId": 74
  },
  {
    "cardId": 160,
    "masterRank": 5,
    "resourceBoxId": 75
  },
  {
    "cardId": 161,
    "masterRank": 1,
    "resourceBoxId": 76
  },
  {
    "cardId": 161,
    "masterRank": 3,
    "resourceBoxId": 77
  },
  {
    "cardId": 161,
    "masterRank": 5,
    "resourceBoxId": 78
  },
  {
    "cardId": 165,
    "masterRank": 1,
    "resourceBoxId": 79
  },
  {
    "cardId": 165,
    "masterRank": 3,
    "resourceBoxId": 80
  },
  {
    "cardId": 165,
    "masterRank": 5,
    "resourceBoxId": 81
  },
  {
    "cardId": 166,
    "masterRank": 1,
    "resourceBoxId": 82
  },
  {
    "cardId": 166,
    "masterRank": 3,
    "resourceBoxId": 83
  },
  {
    "cardId": 166,
    "masterRank": 5,
    "resourceBoxId": 84
  },
  {
    "cardId": 170,
    "masterRank": 1,
    "resourceBoxId": 85
  },
  {
    "cardId": 170,
    "masterRank": 3,
    "resourceBoxId": 86
  },
  {
    "cardId": 170,
    "masterRank": 5,
    "resourceBoxId": 87
  },
  {
    "cardId": 171,
    "masterRank": 1,
    "resourceBoxId": 88
  },
  {
    "cardId": 171,
    "masterRank": 3,
    "resourceBoxId": 89
  },
  {
    "cardId": 171,
    "masterRank": 5,
    "resourceBoxId": 90
  },
  {
    "cardId": 175,
    "masterRank": 1,
    "resourceBoxId": 91
  },
  {
    "cardId": 175,
    "masterRank": 3,
    "resourceBoxId": 92
  },
  {
    "cardId": 175,
    "masterRank": 5,
    "resourceBoxId": 93
  },
  {
    "cardId": 176,
    "masterRank": 1,
    "resourceBoxId": 94
  },
  {
    "cardId": 176,
    "masterRank": 3,
    "resourceBoxId": 95
  },
  {
    "cardId": 176,
    "masterRank": 5,
    "resourceBoxId": 96
  },
  {
    "cardId": 180,
    "masterRank": 1,
    "resourceBoxId": 97
  },
  {
    "cardId": 180,
    "masterRank": 2,
    "resourceBoxId": 98
  },
  {
    "cardId": 180,
    "masterRank": 3,
    "resourceBoxId": 99
  },
  {
    "cardId": 180,
    "masterRank": 5,
    "resourceBoxId": 100
  },
  {
    "cardId": 181,
    "masterRank": 1,
    "resourceBoxId": 101
  },
  {
    "cardId": 181,
    "masterRank": 2,
    "resourceBoxId": 102
  },
  {
    "cardId": 181,
    "masterRank": 3,
    "resourceBoxId": 103
  },
  {
    "cardId": 181,
    "masterRank": 5,
    "resourceBoxId": 104
  },
  {
    "cardId": 185,
    "masterRank": 1,
    "resourceBoxId": 105
  },
  {
    "cardId": 185,
    "masterRank": 3,
    "resourceBoxId": 106
  },
  {
    "cardId": 185,
    "masterRank": 5,
    "resourceBoxId": 107
  },
  {
    "cardId": 186,
    "masterRank": 1,
    "resourceBoxId": 108
  },
  {
    "cardId": 186,
    "masterRank": 3,
    "resourceBoxId": 109
  },
  {
    "cardId": 186,
    "masterRank": 5,
    "resourceBoxId": 110
  },
  {
    "cardId": 190,
    "masterRank": 1,
    "resourceBoxId": 111
  },
  {
    "cardId": 190,
    "masterRank": 3,
    "resourceBoxId": 112
  },
  {
    "cardId": 190,
    "masterRank": 5,
    "resourceBoxId": 113
  },
  {
    "cardId": 191,
    "masterRank": 1,
    "resourceBoxId": 114
  },
  {
    "cardId": 191,
    "masterRank": 3,
    "resourceBoxId": 115
  },
  {
    "cardId": 191,
    "masterRank": 5,
    "resourceBoxId": 116
  },
  {
    "cardId": 195,
    "masterRank": 1,
    "resourceBoxId": 117
  },
  {
    "cardId": 195,
    "masterRank": 2,
    "resourceBoxId": 118
  },
  {
    "cardId": 195,
    "masterRank": 3,
    "resourceBoxId": 119
  },
  {
    "cardId": 195,
    "masterRank": 5,
    "resourceBoxId": 120
  },
  {
    "cardId": 196,
    "masterRank": 1,
    "resourceBoxId": 121
  },
  {
    "cardId": 196,
    "masterRank": 2,
    "resourceBoxId": 122
  },
  {
    "cardId": 196,
    "masterRank": 3,
    "resourceBoxId": 123
  },
  {
    "cardId": 196,
    "masterRank": 5,
    "resourceBoxId": 124
  },
  {
    "cardId": 197,
    "masterRank": 1,
    "resourceBoxId": 125
  },
  {
    "cardId": 197,
    "masterRank": 3,
    "resourceBoxId": 126
  },
  {
    "cardId": 197,
    "masterRank": 5,
    "resourceBoxId": 127
  },
  {
    "cardId": 198,
    "masterRank": 1,
    "resourceBoxId": 128
  },
  {
    "cardId": 198,
    "masterRank": 3,
    "resourceBoxId": 129
  },
  {
    "cardId": 198,
    "masterRank": 5,
    "resourceBoxId": 130
  },
  {
    "cardId": 202,
    "masterRank": 1,
    "resourceBoxId": 131
  },
  {
    "cardId": 202,
    "masterRank": 3,
    "resourceBoxId": 132
  },
  {
    "cardId": 202,
    "masterRank": 5,
    "resourceBoxId": 133
  },
  {
    "cardId": 203,
    "masterRank": 1,
    "resourceBoxId": 134
  },
  {
    "cardId": 203,
    "masterRank": 3,
    "resourceBoxId": 135
  },
  {
    "cardId": 203,
    "masterRank": 5,
    "resourceBoxId": 136
  },
  {
    "cardId": 207,
    "masterRank": 1,
    "resourceBoxId": 137
  },
  {
    "cardId": 207,
    "masterRank": 3,
    "resourceBoxId": 138
  },
  {
    "cardId": 207,
    "masterRank": 5,
    "resourceBoxId": 139
  },
  {
    "cardId": 208,
    "masterRank": 1,
    "resourceBoxId": 140
  },
  {
    "cardId": 208,
    "masterRank": 3,
    "resourceBoxId": 141
  },
  {
    "cardId": 208,
    "masterRank": 5,
    "resourceBoxId": 142
  },
  {
    "cardId": 212,
    "masterRank": 1,
    "resourceBoxId": 143
  },
  {
    "cardId": 212,
    "masterRank": 2,
    "resourceBoxId": 144
  },
  {
    "cardId": 212,
    "masterRank": 3,
    "resourceBoxId": 145
  },
  {
    "cardId": 212,
    "masterRank": 5,
    "resourceBoxId": 146
  },
  {
    "cardId": 213,
    "masterRank": 1,
    "resourceBoxId": 147
  },
  {
    "cardId": 213,
    "masterRank": 2,
    "resourceBoxId": 148
  },
  {
    "cardId": 213,
    "masterRank": 3,
    "resourceBoxId": 149
  },
  {
    "cardId": 213,
    "masterRank": 5,
    "resourceBoxId": 150
  },
  {
    "cardId": 217,
    "masterRank": 1,
    "resourceBoxId": 151
  },
  {
    "cardId": 217,
    "masterRank": 3,
    "resourceBoxId": 152
  },
  {
    "cardId": 217,
    "masterRank": 5,
    "resourceBoxId": 153
  },
  {
    "cardId": 218,
    "masterRank": 1,
    "resourceBoxId": 154
  },
  {
    "cardId": 218,
    "masterRank": 3,
    "resourceBoxId": 155
  },
  {
    "cardId": 218,
    "masterRank": 5,
    "resourceBoxId": 156
  },
  {
    "cardId": 222,
    "masterRank": 1,
    "resourceBoxId": 157
  },
  {
    "cardId": 222,
    "masterRank": 3,
    "resourceBoxId": 158
  },
  {
    "cardId": 222,
    "masterRank": 5,
    "resourceBoxId": 159
  },
  {
    "cardId": 223,
    "masterRank": 1,
    "resourceBoxId": 160
  },
  {
    "cardId": 223,
    "masterRank": 3,
    "resourceBoxId": 161
  },
  {
    "cardId": 223,
    "masterRank": 5,
    "resourceBoxId": 162
  },
  {
    "cardId": 227,
    "masterRank": 1,
    "resourceBoxId": 163
  },
  {
    "cardId": 227,
    "masterRank": 2,
    "resourceBoxId": 164
  },
  {
    "cardId": 227,
    "masterRank": 3,
    "resourceBoxId": 165
  },
  {
    "cardId": 227,
    "masterRank": 5,
    "resourceBoxId": 166
  },
  {
    "cardId": 228,
    "masterRank": 1,
    "resourceBoxId": 167
  },
  {
    "cardId": 228,
    "masterRank": 2,
    "resourceBoxId": 168
  },
  {
    "cardId": 228,
    "masterRank": 3,
    "resourceBoxId": 169
  },
  {
    "cardId": 228,
    "masterRank": 5,
    "resourceBoxId": 170
  },
  {
    "cardId": 232,
    "masterRank": 1,
    "resourceBoxId": 171
  },
  {
    "cardId": 232,
    "masterRank": 3,
    "resourceBoxId": 172
  },
  {
    "cardId": 232,
    "masterRank": 5,
    "resourceBoxId": 173
  },
  {
    "cardId": 233,
    "masterRank": 1,
    "resourceBoxId": 174
  },
  {
    "cardId": 233,
    "masterRank": 3,
    "resourceBoxId": 175
  },
  {
    "cardId": 233,
    "masterRank": 5,
    "resourceBoxId": 176
  },
  {
    "cardId": 237,
    "masterRank": 1,
    "resourceBoxId": 177
  },
  {
    "cardId": 237,
    "masterRank": 3,
    "resourceBoxId": 178
  },
  {
    "cardId": 237,
    "masterRank": 5,
    "resourceBoxId": 179
  },
  {
    "cardId": 238,
    "masterRank": 1,
    "resourceBoxId": 180
  },
  {
    "cardId": 238,
    "masterRank": 3,
    "resourceBoxId": 181
  },
  {
    "cardId": 238,
    "masterRank": 5,
    "resourceBoxId": 182
  },
  {
    "cardId": 242,
    "masterRank": 1,
    "resourceBoxId": 183
  },
  {
    "cardId": 242,
    "masterRank": 2,
    "resourceBoxId": 184
  },
  {
    "cardId": 242,
    "masterRank": 3,
    "resourceBoxId": 185
  },
  {
    "cardId": 242,
    "masterRank": 5,
    "resourceBoxId": 186
  },
  {
    "cardId": 243,
    "masterRank": 1,
    "resourceBoxId": 187
  },
  {
    "cardId": 243,
    "masterRank": 2,
    "resourceBoxId": 188
  },
  {
    "cardId": 243,
    "masterRank": 3,
    "resourceBoxId": 189
  },
  {
    "cardId": 243,
    "masterRank": 5,
    "resourceBoxId": 190
  },
  {
    "cardId": 244,
    "masterRank": 1,
    "resourceBoxId": 191
  },
  {
    "cardId": 244,
    "masterRank": 3,
    "resourceBoxId": 192
  },
  {
    "cardId": 244,
    "masterRank": 5,
    "resourceBoxId": 193
  },
  {
    "cardId": 245,
    "masterRank": 1,
    "resourceBoxId": 194
  },
  {
    "cardId": 245,
    "masterRank": 3,
    "resourceBoxId": 195
  },
  {
    "cardId": 245,
    "masterRank": 5,
    "resourceBoxId": 196
  },
  {
    "cardId": 249,
    "masterRank": 1,
    "resourceBoxId": 197
  },
  {
    "cardId": 249,
    "masterRank": 3,
    "resourceBoxId": 198
  },
  {
    "cardId": 249,
    "masterRank": 5,
    "resourceBoxId": 199
  },
  {
    "cardId": 250,
    "masterRank": 1,
    "resourceBoxId": 200
  },
  {
    "cardId": 250,
    "masterRank": 3,
    "resourceBoxId": 201
  },
  {
    "cardId": 250,
    "masterRank": 5,
    "resourceBoxId": 202
  },
  {
    "cardId": 254,
    "masterRank": 1,
    "resourceBoxId": 203
  },
  {
    "cardId": 254,
    "masterRank": 3,
    "resourceBoxId": 204
  },
  {
    "cardId": 254,
    "masterRank": 5,
    "resourceBoxId": 205
  },
  {
    "cardId": 255,
    "masterRank": 1,
    "resourceBoxId": 206
  },
  {
    "cardId": 255,
    "masterRank": 3,
    "resourceBoxId": 207
  },
  {
    "cardId": 255,
    "masterRank": 5,
    "resourceBoxId": 208
  },
  {
    "cardId": 259,
    "masterRank": 1,
    "resourceBoxId": 209
  },
  {
    "cardId": 259,
    "masterRank": 2,
    "resourceBoxId": 210
  },
  {
    "cardId": 259,
    "masterRank": 3,
    "resourceBoxId": 211
  },
  {
    "cardId": 259,
    "masterRank": 5,
    "resourceBoxId": 212
  },
  {
    "cardId": 260,
    "masterRank": 1,
    "resourceBoxId": 213
  },
  {
    "cardId": 260,
    "masterRank": 2,
    "resourceBoxId": 214
  },
  {
    "cardId": 260,
    "masterRank": 3,
    "resourceBoxId": 215
  },
  {
    "cardId": 260,
    "masterRank": 5,
    "resourceBoxId": 216
  },
  {
    "cardId": 335,
    "masterRank": 1,
    "resourceBoxId": 315
  },
  {
    "cardId": 335,
    "masterRank": 3,
    "resourceBoxId": 316
  },
  {
    "cardId": 335,
    "masterRank": 5,
    "resourceBoxId": 317
  },
  {
    "cardId": 335,
    "masterRank": 2,
    "resourceBoxId": 318
  },
  {
    "cardId": 336,
    "masterRank": 1,
    "resourceBoxId": 319
  },
  {
    "cardId": 336,
    "masterRank": 3,
    "resourceBoxId": 320
  },
  {
    "cardId": 336,
    "masterRank": 5,
    "resourceBoxId": 321
  },
  {
    "cardId": 336,
    "masterRank": 2,
    "resourceBoxId": 322
  },
  {
    "cardId": 337,
    "masterRank": 1,
    "resourceBoxId": 323
  },
  {
    "cardId": 337,
    "masterRank": 3,
    "resourceBoxId": 324
  },
  {
    "cardId": 337,
    "masterRank": 5,
    "resourceBoxId": 325
  },
  {
    "cardId": 337,
    "masterRank": 2,
    "resourceBoxId": 326
  },
  {
    "cardId": 338,
    "masterRank": 1,
    "resourceBoxId": 327
  },
  {
    "cardId": 338,
    "masterRank": 3,
    "resourceBoxId": 328
  },
  {
    "cardId": 338,
    "masterRank": 5,
    "resourceBoxId": 329
  },
  {
    "cardId": 338,
    "masterRank": 2,
    "resourceBoxId": 330
  },
  {
    "cardId": 339,
    "masterRank": 1,
    "resourceBoxId": 331
  },
  {
    "cardId": 339,
    "masterRank": 3,
    "resourceBoxId": 332
  },
  {
    "cardId": 339,
    "masterRank": 5,
    "resourceBoxId": 333
  },
  {
    "cardId": 339,
    "masterRank": 2,
    "resourceBoxId": 334
  }
]