[
  {
    "id": 1,
    "mysekaiConvertItemTabType": "normal",
    "seq": 10,
    "name": "아이템",
    "assetbundleName": "icon_live_item"
  },
  {
    "id": 2,
    "mysekaiConvertItemTabType": "tone",
    "seq": 20,
    "name": "음색",
    "assetbundleName": "icon_material_tone"
  },
  {
    "id": 3,
    "mysekaiConvertItemTabType": "mysekai_blueprint",
    "seq": 30,
    "name": "설계도",
    "assetbundleName": "icon_blueprint"
  },
  {
    "id": 4,
    "mysekaiConvertItemTabType": "mysekai_music_record",
    "seq": 40,
    "name": "레코드",
    "assetbundleName": "icon_record_jacket"
  },
  {
    "id": 5,
    "mysekaiConvertItemTabType": "limited",
    "seq": 50,
    "name": "기간 한정",
    "assetbundleName": "icon_limited_edition"
  }
]