[
  {
    "id": 1,
    "name": "초기 판매",
    "virtualShopItems": [
      {
        "id": 1,
        "virtualShopId": 1,
        "virtualShopItemType": "avatar_motion",
        "seq": 10,
        "resourceBoxId": 1,
        "costVirtualCoin": 1500,
        "costJewel": 500,
        "startAt": 1556679600000
      },
      {
        "id": 2,
        "virtualShopId": 1,
        "virtualShopItemType": "avatar_motion",
        "seq": 20,
        "resourceBoxId": 2,
        "costVirtualCoin": 1500,
        "costJewel": 500,
        "startAt": 1556679600000
      },
      {
        "id": 3,
        "virtualShopId": 1,
        "virtualShopItemType": "avatar_motion",
        "seq": 30,
        "resourceBoxId": 3,
        "costVirtualCoin": 1500,
        "costJewel": 500,
        "startAt": 1556679600000
      },
      {
        "id": 4,
        "virtualShopId": 1,
        "virtualShopItemType": "avatar_motion",
        "seq": 40,
        "resourceBoxId": 4,
        "costVirtualCoin": 1500,
        "costJewel": 500,
        "startAt": 1556679600000
      },
      {
        "id": 5,
        "virtualShopId": 1,
        "virtualShopItemType": "avatar_motion",
        "seq": 50,
        "resourceBoxId": 5,
        "costVirtualCoin": 1500,
        "costJewel": 500,
        "startAt": 1556679600000
      },
      {
        "id": 6,
        "virtualShopId": 1,
        "virtualShopItemType": "avatar_motion",
        "seq": 60,
        "resourceBoxId": 6,
        "costVirtualCoin": 1500,
        "costJewel": 500,
        "startAt": 1556679600000
      },
      {
        "id": 7,
        "virtualShopId": 1,
        "virtualShopItemType": "avatar_motion",
        "seq": 70,
        "resourceBoxId": 7,
        "costVirtualCoin": 1500,
        "costJewel": 500,
        "startAt": 1556679600000
      },
      {
        "id": 8,
        "virtualShopId": 1,
        "virtualShopItemType": "avatar_motion",
        "seq": 80,
        "resourceBoxId": 8,
        "costVirtualCoin": 1500,
        "costJewel": 500,
        "startAt": 1556679600000
      },
      {
        "id": 9,
        "virtualShopId": 1,
        "virtualShopItemType": "avatar_motion",
        "seq": 90,
        "resourceBoxId": 9,
        "costVirtualCoin": 1500,
        "costJewel": 500,
        "startAt": 1556679600000
      },
      {
        "id": 10,
        "virtualShopId": 1,
        "virtualShopItemType": "avatar_motion",
        "seq": 100,
        "resourceBoxId": 10,
        "costVirtualCoin": 1500,
        "costJewel": 500,
        "startAt": 1556679600000
      },
      {
        "id": 11,
        "virtualShopId": 1,
        "virtualShopItemType": "avatar_motion",
        "seq": 110,
        "resourceBoxId": 11,
        "costVirtualCoin": 1500,
        "costJewel": 500,
        "startAt": 1556679600000
      },
      {
        "id": 12,
        "virtualShopId": 1,
        "virtualShopItemType": "avatar_motion",
        "seq": 120,
        "resourceBoxId": 12,
        "costVirtualCoin": 1500,
        "costJewel": 500,
        "startAt": 1556679600000
      },
      {
        "id": 13,
        "virtualShopId": 1,
        "virtualShopItemType": "avatar_motion",
        "seq": 130,
        "resourceBoxId": 13,
        "costVirtualCoin": 1500,
        "costJewel": 500,
        "startAt": 1556679600000
      },
      {
        "id": 14,
        "virtualShopId": 1,
        "virtualShopItemType": "avatar_motion",
        "seq": 140,
        "resourceBoxId": 14,
        "costVirtualCoin": 1500,
        "costJewel": 500,
        "startAt": 1556679600000
      },
      {
        "id": 15,
        "virtualShopId": 1,
        "virtualShopItemType": "avatar_motion",
        "seq": 150,
        "resourceBoxId": 15,
        "costVirtualCoin": 1500,
        "costJewel": 500,
        "startAt": 1556679600000
      },
      {
        "id": 16,
        "virtualShopId": 1,
        "virtualShopItemType": "avatar_motion",
        "seq": 160,
        "resourceBoxId": 16,
        "costVirtualCoin": 1500,
        "costJewel": 500,
        "startAt": 1556679600000
      },
      {
        "id": 17,
        "virtualShopId": 1,
        "virtualShopItemType": "avatar_motion",
        "seq": 170,
        "resourceBoxId": 17,
        "costVirtualCoin": 1500,
        "costJewel": 500,
        "startAt": 1556679600000
      },
      {
        "id": 18,
        "virtualShopId": 1,
        "virtualShopItemType": "avatar_motion",
        "seq": 180,
        "resourceBoxId": 18,
        "costVirtualCoin": 1500,
        "costJewel": 500,
        "startAt": 1556679600000
      },
      {
        "id": 19,
        "virtualShopId": 1,
        "virtualShopItemType": "avatar_motion",
        "seq": 190,
        "resourceBoxId": 19,
        "costVirtualCoin": 1500,
        "costJewel": 500,
        "startAt": 1556679600000
      },
      {
        "id": 20,
        "virtualShopId": 1,
        "virtualShopItemType": "avatar_motion",
        "seq": 200,
        "resourceBoxId": 20,
        "costVirtualCoin": 1500,
        "costJewel": 500,
        "startAt": 1556679600000
      },
      {
        "id": 21,
        "virtualShopId": 1,
        "virtualShopItemType": "avatar_motion",
        "seq": 210,
        "resourceBoxId": 21,
        "costVirtualCoin": 1500,
        "costJewel": 500,
        "startAt": 1556679600000
      },
      {
        "id": 22,
        "virtualShopId": 1,
        "virtualShopItemType": "avatar_motion",
        "seq": 220,
        "resourceBoxId": 22,
        "costVirtualCoin": 1500,
        "costJewel": 500,
        "startAt": 1556679600000
      },
      {
        "id": 23,
        "virtualShopId": 1,
        "virtualShopItemType": "avatar_motion",
        "seq": 230,
        "resourceBoxId": 23,
        "costVirtualCoin": 1500,
        "costJewel": 500,
        "startAt": 1556679600000
      },
      {
        "id": 24,
        "virtualShopId": 1,
        "virtualShopItemType": "avatar_motion",
        "seq": 240,
        "resourceBoxId": 24,
        "costVirtualCoin": 1500,
        "costJewel": 500,
        "startAt": 1556679600000
      },
      {
        "id": 25,
        "virtualShopId": 1,
        "virtualShopItemType": "avatar_motion",
        "seq": 250,
        "resourceBoxId": 25,
        "costVirtualCoin": 1500,
        "costJewel": 500,
        "startAt": 1556679600000
      },
      {
        "id": 26,
        "virtualShopId": 1,
        "virtualShopItemType": "avatar_motion",
        "seq": 260,
        "resourceBoxId": 26,
        "costVirtualCoin": 1500,
        "costJewel": 500,
        "startAt": 1556679600000
      },
      {
        "id": 27,
        "virtualShopId": 1,
        "virtualShopItemType": "avatar_motion",
        "seq": 270,
        "resourceBoxId": 27,
        "costVirtualCoin": 1500,
        "costJewel": 500,
        "startAt": 1556679600000
      },
      {
        "id": 28,
        "virtualShopId": 1,
        "virtualShopItemType": "costume",
        "seq": 10,
        "resourceBoxId": 33,
        "costVirtualCoin": 3000,
        "costJewel": 1000,
        "startAt": 1556679600000
      },
      {
        "id": 29,
        "virtualShopId": 1,
        "virtualShopItemType": "costume",
        "seq": 20,
        "resourceBoxId": 28,
        "costVirtualCoin": 3000,
        "costJewel": 1000,
        "startAt": 1556679600000
      },
      {
        "id": 30,
        "virtualShopId": 1,
        "virtualShopItemType": "costume",
        "seq": 30,
        "resourceBoxId": 29,
        "costVirtualCoin": 3000,
        "costJewel": 1000,
        "startAt": 1556679600000
      },
      {
        "id": 31,
        "virtualShopId": 1,
        "virtualShopItemType": "costume",
        "seq": 40,
        "resourceBoxId": 30,
        "costVirtualCoin": 3000,
        "costJewel": 1000,
        "startAt": 1556679600000
      },
      {
        "id": 32,
        "virtualShopId": 1,
        "virtualShopItemType": "costume",
        "seq": 50,
        "resourceBoxId": 31,
        "costVirtualCoin": 3000,
        "costJewel": 1000,
        "startAt": 1556679600000
      },
      {
        "id": 33,
        "virtualShopId": 1,
        "virtualShopItemType": "costume",
        "seq": 60,
        "resourceBoxId": 32,
        "costVirtualCoin": 3000,
        "costJewel": 1000,
        "startAt": 1556679600000
      },
      {
        "id": 34,
        "virtualShopId": 1,
        "virtualShopItemType": "costume",
        "seq": 70,
        "resourceBoxId": 58,
        "costVirtualCoin": 3000,
        "costJewel": 1000,
        "startAt": 1556679600000
      },
      {
        "id": 35,
        "virtualShopId": 1,
        "virtualShopItemType": "costume",
        "seq": 80,
        "resourceBoxId": 59,
        "costVirtualCoin": 3000,
        "costJewel": 1000,
        "startAt": 1556679600000
      },
      {
        "id": 36,
        "virtualShopId": 1,
        "virtualShopItemType": "accessory",
        "seq": 199991,
        "resourceBoxId": 34,
        "costVirtualCoin": 3000,
        "costJewel": 1000,
        "startAt": 1556679600000
      },
      {
        "id": 37,
        "virtualShopId": 1,
        "virtualShopItemType": "accessory",
        "seq": 199992,
        "resourceBoxId": 35,
        "costVirtualCoin": 3000,
        "costJewel": 1000,
        "startAt": 1556679600000
      },
      {
        "id": 38,
        "virtualShopId": 1,
        "virtualShopItemType": "accessory",
        "seq": 199993,
        "resourceBoxId": 36,
        "costVirtualCoin": 3000,
        "costJewel": 1000,
        "startAt": 1556679600000
      },
      {
        "id": 39,
        "virtualShopId": 1,
        "virtualShopItemType": "accessory",
        "seq": 199994,
        "resourceBoxId": 37,
        "costVirtualCoin": 3000,
        "costJewel": 1000,
        "startAt": 1556679600000
      },
      {
        "id": 40,
        "virtualShopId": 1,
        "virtualShopItemType": "accessory",
        "seq": 199995,
        "resourceBoxId": 38,
        "costVirtualCoin": 3000,
        "costJewel": 1000,
        "startAt": 1556679600000
      },
      {
        "id": 41,
        "virtualShopId": 1,
        "virtualShopItemType": "accessory",
        "seq": 199996,
        "resourceBoxId": 39,
        "costVirtualCoin": 3000,
        "costJewel": 1000,
        "startAt": 1556679600000
      },
      {
        "id": 42,
        "virtualShopId": 1,
        "virtualShopItemType": "accessory",
        "seq": 199997,
        "resourceBoxId": 40,
        "costVirtualCoin": 3000,
        "costJewel": 1000,
        "startAt": 1556679600000
      },
      {
        "id": 43,
        "virtualShopId": 1,
        "virtualShopItemType": "accessory",
        "seq": 199998,
        "resourceBoxId": 41,
        "costVirtualCoin": 3000,
        "costJewel": 1000,
        "startAt": 1556679600000
      },
      {
        "id": 44,
        "virtualShopId": 1,
        "virtualShopItemType": "accessory",
        "seq": 199999,
        "resourceBoxId": 42,
        "costVirtualCoin": 3000,
        "costJewel": 1000,
        "startAt": 1556679600000
      },
      {
        "id": 45,
        "virtualShopId": 1,
        "virtualShopItemType": "accessory",
        "seq": 200000,
        "resourceBoxId": 43,
        "costVirtualCoin": 3000,
        "costJewel": 1000,
        "startAt": 1556679600000
      },
      {
        "id": 46,
        "virtualShopId": 1,
        "virtualShopItemType": "coordinate",
        "seq": 199986,
        "resourceBoxId": 44,
        "costPaidJewel": 1000,
        "startAt": 1556679600000
      },
      {
        "id": 47,
        "virtualShopId": 1,
        "virtualShopItemType": "coordinate",
        "seq": 199987,
        "resourceBoxId": 45,
        "costPaidJewel": 1000,
        "startAt": 1556679600000
      },
      {
        "id": 48,
        "virtualShopId": 1,
        "virtualShopItemType": "coordinate",
        "seq": 199988,
        "resourceBoxId": 46,
        "costPaidJewel": 1000,
        "startAt": 1556679600000
      },
      {
        "id": 49,
        "virtualShopId": 1,
        "virtualShopItemType": "coordinate",
        "seq": 199989,
        "resourceBoxId": 47,
        "costPaidJewel": 1000,
        "startAt": 1556679600000
      },
      {
        "id": 50,
        "virtualShopId": 1,
        "virtualShopItemType": "coordinate",
        "seq": 199990,
        "resourceBoxId": 48,
        "costPaidJewel": 1000,
        "startAt": 1556679600000
      },
      {
        "id": 51,
        "virtualShopId": 1,
        "virtualShopItemType": "penlight",
        "seq": 199985,
        "resourceBoxId": 49,
        "costPaidJewel": 1000,
        "startAt": 1556679600000
      },
      {
        "id": 52,
        "virtualShopId": 1,
        "virtualShopItemType": "coordinate",
        "seq": 100000,
        "resourceBoxId": 61,
        "costPaidJewel": 1000,
        "startAt": 1664776800000,
        "endAt": 1665035999000
      }
    ],
    "virtualShopType": "other"
  },
  {
    "id": 2,
    "name": "제1회 이벤트 판매",
    "virtualShopItems": [
      {
        "id": 53,
        "virtualShopId": 2,
        "virtualShopItemType": "penlight",
        "seq": 199984,
        "resourceBoxId": 50,
        "costPaidJewel": 1000,
        "startAt": 1653112800000
      }
    ],
    "virtualShopType": "event"
  },
  {
    "id": 3,
    "name": "제2회 이벤트 판매",
    "virtualShopItems": [
      {
        "id": 54,
        "virtualShopId": 3,
        "virtualShopItemType": "coordinate",
        "seq": 199983,
        "resourceBoxId": 60,
        "costPaidJewel": 1000,
        "startAt": 1653804000000
      }
    ],
    "virtualShopType": "event"
  },
  {
    "id": 4,
    "name": "호나미 BIRTHDAY",
    "virtualShopItems": [
      {
        "id": 55,
        "virtualShopId": 4,
        "virtualShopItemType": "coordinate",
        "seq": 99999,
        "resourceBoxId": 62,
        "costPaidJewel": 1000,
        "startAt": 1666677600000,
        "endAt": 1666936799000
      }
    ],
    "virtualShopType": "birthday"
  },
  {
    "id": 6,
    "name": "제3회 이벤트 판매",
    "virtualShopItems": [
      {
        "id": 58,
        "virtualShopId": 6,
        "virtualShopItemType": "coordinate",
        "seq": 199982,
        "resourceBoxId": 55,
        "costPaidJewel": 1000,
        "startAt": 1654495200000
      }
    ],
    "virtualShopType": "event"
  },
  {
    "id": 9,
    "name": "제5회 이벤트 판매",
    "virtualShopItems": [
      {
        "id": 61,
        "virtualShopId": 9,
        "virtualShopItemType": "penlight",
        "seq": 199981,
        "resourceBoxId": 51,
        "costPaidJewel": 1000,
        "startAt": 1656568800000
      }
    ],
    "virtualShopType": "event"
  },
  {
    "id": 10,
    "name": "제6회 이벤트 판매",
    "virtualShopItems": [
      {
        "id": 62,
        "virtualShopId": 10,
        "virtualShopItemType": "accessory",
        "seq": 199980,
        "resourceBoxId": 56,
        "costVirtualCoin": 3000,
        "costJewel": 1000,
        "startAt": 1655877600000
      }
    ],
    "virtualShopType": "event"
  },
  {
    "id": 12,
    "name": "제7회 이벤트 판매",
    "virtualShopItems": [
      {
        "id": 64,
        "virtualShopId": 12,
        "virtualShopItemType": "penlight",
        "seq": 199979,
        "resourceBoxId": 65,
        "costPaidJewel": 1000,
        "startAt": 1657951200000
      }
    ],
    "virtualShopType": "event"
  },
  {
    "id": 19,
    "name": "제10회 이벤트 판매",
    "virtualShopItems": [
      {
        "id": 74,
        "virtualShopId": 19,
        "virtualShopItemType": "penlight",
        "seq": 199978,
        "resourceBoxId": 74,
        "costPaidJewel": 1000,
        "startAt": 1659333600000
      }
    ],
    "virtualShopType": "event"
  },
  {
    "id": 20,
    "name": "제11회 이벤트 판매",
    "virtualShopItems": [
      {
        "id": 75,
        "virtualShopId": 20,
        "virtualShopItemType": "penlight",
        "seq": 199977,
        "resourceBoxId": 75,
        "costPaidJewel": 1000,
        "startAt": 1662098400000
      }
    ],
    "virtualShopType": "event"
  },
  {
    "id": 23,
    "name": "제12회 이벤트 판매",
    "virtualShopItems": [
      {
        "id": 78,
        "virtualShopId": 23,
        "virtualShopItemType": "penlight",
        "seq": 199976,
        "resourceBoxId": 78,
        "costPaidJewel": 1000,
        "startAt": 1660024800000
      }
    ],
    "virtualShopType": "event"
  },
  {
    "id": 27,
    "name": "제14회 이벤트 판매",
    "virtualShopItems": [
      {
        "id": 82,
        "virtualShopId": 27,
        "virtualShopItemType": "penlight",
        "seq": 199975,
        "resourceBoxId": 83,
        "costPaidJewel": 1000,
        "startAt": 1661407200000
      }
    ],
    "virtualShopType": "event"
  },
  {
    "id": 29,
    "name": "제15회 이벤트 판매",
    "virtualShopItems": [
      {
        "id": 84,
        "virtualShopId": 29,
        "virtualShopItemType": "accessory",
        "seq": 199974,
        "resourceBoxId": 84,
        "costVirtualCoin": 3000,
        "costJewel": 1000,
        "startAt": 1662789600000
      }
    ],
    "virtualShopType": "event"
  },
  {
    "id": 30,
    "name": "제16회 이벤트 판매",
    "virtualShopItems": [
      {
        "id": 85,
        "virtualShopId": 30,
        "virtualShopItemType": "penlight",
        "seq": 199973,
        "resourceBoxId": 85,
        "costPaidJewel": 1000,
        "startAt": 1663480800000
      }
    ],
    "virtualShopType": "event"
  },
  {
    "id": 33,
    "name": "제17회 이벤트 판매",
    "virtualShopItems": [
      {
        "id": 88,
        "virtualShopId": 33,
        "virtualShopItemType": "penlight",
        "seq": 199972,
        "resourceBoxId": 88,
        "costPaidJewel": 1000,
        "startAt": 1664172000000
      }
    ],
    "virtualShopType": "event"
  },
  {
    "id": 34,
    "name": "제18회 이벤트 판매",
    "virtualShopItems": [
      {
        "id": 89,
        "virtualShopId": 34,
        "virtualShopItemType": "penlight",
        "seq": 199971,
        "resourceBoxId": 89,
        "costPaidJewel": 1000,
        "startAt": 1664776800000
      },
      {
        "id": 90,
        "virtualShopId": 34,
        "virtualShopItemType": "penlight",
        "seq": 199970,
        "resourceBoxId": 90,
        "costVirtualCoin": 6000,
        "costJewel": 2000,
        "startAt": 1664776800000
      },
      {
        "id": 91,
        "virtualShopId": 34,
        "virtualShopItemType": "accessory",
        "seq": 199969,
        "resourceBoxId": 91,
        "costVirtualCoin": 3000,
        "costJewel": 1000,
        "startAt": 1664776800000
      }
    ],
    "virtualShopType": "event"
  },
  {
    "id": 35,
    "name": "제19회 이벤트 판매",
    "virtualShopItems": [
      {
        "id": 92,
        "virtualShopId": 35,
        "virtualShopItemType": "penlight",
        "seq": 199968,
        "resourceBoxId": 92,
        "costPaidJewel": 1000,
        "startAt": 1665381600000
      }
    ],
    "virtualShopType": "event"
  },
  {
    "id": 37,
    "name": "제20회 이벤트 판매",
    "virtualShopItems": [
      {
        "id": 94,
        "virtualShopId": 37,
        "virtualShopItemType": "penlight",
        "seq": 199967,
        "resourceBoxId": 94,
        "costPaidJewel": 1000,
        "startAt": 1665986400000
      }
    ],
    "virtualShopType": "event"
  },
  {
    "id": 39,
    "name": "제21회 이벤트 판매",
    "virtualShopItems": [
      {
        "id": 96,
        "virtualShopId": 39,
        "virtualShopItemType": "penlight",
        "seq": 199966,
        "resourceBoxId": 96,
        "costPaidJewel": 1000,
        "startAt": 1666591200000
      }
    ],
    "virtualShopType": "event"
  },
  {
    "id": 44,
    "name": "토우야 BIRTHDAY",
    "virtualShopItems": [
      {
        "id": 102,
        "virtualShopId": 44,
        "virtualShopItemType": "coordinate",
        "seq": 99974,
        "resourceBoxId": 102,
        "costPaidJewel": 1000,
        "startAt": 1653285600000,
        "endAt": 1653544799000
      }
    ],
    "virtualShopType": "birthday"
  },
  {
    "id": 48,
    "name": "루이 BIRTHDAY",
    "virtualShopItems": [
      {
        "id": 107,
        "virtualShopId": 48,
        "virtualShopItemType": "coordinate",
        "seq": 99973,
        "resourceBoxId": 107,
        "costPaidJewel": 1000,
        "startAt": 1655877600000,
        "endAt": 1656136799000
      }
    ],
    "virtualShopType": "birthday"
  },
  {
    "id": 50,
    "name": "칠석 라이브",
    "virtualShopItems": [
      {
        "id": 110,
        "virtualShopId": 50,
        "virtualShopItemType": "accessory",
        "seq": 99972,
        "resourceBoxId": 110,
        "costVirtualCoin": 3000,
        "costJewel": 1000,
        "startAt": 1659420000000,
        "endAt": 1659765599000
      }
    ],
    "virtualShopType": "special_live"
  },
  {
    "id": 52,
    "name": "네네 BIRTHDAY",
    "virtualShopItems": [
      {
        "id": 112,
        "virtualShopId": 52,
        "virtualShopItemType": "coordinate",
        "seq": 99971,
        "resourceBoxId": 112,
        "costPaidJewel": 1000,
        "startAt": 1658124000000,
        "endAt": 1658383199000
      }
    ],
    "virtualShopType": "birthday"
  },
  {
    "id": 54,
    "name": "안 BIRTHDAY",
    "virtualShopItems": [
      {
        "id": 114,
        "virtualShopId": 54,
        "virtualShopItemType": "coordinate",
        "seq": 99970,
        "resourceBoxId": 114,
        "costPaidJewel": 1000,
        "startAt": 1658642400000,
        "endAt": 1658901599000
      }
    ],
    "virtualShopType": "birthday"
  },
  {
    "id": 56,
    "name": "이치카 BIRTHDAY",
    "virtualShopItems": [
      {
        "id": 117,
        "virtualShopId": 56,
        "virtualShopItemType": "coordinate",
        "seq": 99969,
        "resourceBoxId": 117,
        "costPaidJewel": 1000,
        "startAt": 1660024800000,
        "endAt": 1660283999000
      }
    ],
    "virtualShopType": "birthday"
  },
  {
    "id": 59,
    "name": "미즈키 BIRTHDAY",
    "virtualShopItems": [
      {
        "id": 120,
        "virtualShopId": 59,
        "virtualShopItemType": "coordinate",
        "seq": 99968,
        "resourceBoxId": 120,
        "costPaidJewel": 1000,
        "startAt": 1661407200000,
        "endAt": 1661666399000
      }
    ],
    "virtualShopType": "birthday"
  },
  {
    "id": 60,
    "name": "미쿠 ANNIVERSARY",
    "virtualShopItems": [
      {
        "id": 121,
        "virtualShopId": 60,
        "virtualShopItemType": "coordinate",
        "seq": 99968,
        "resourceBoxId": 121,
        "costPaidJewel": 1000,
        "startAt": 1661752800000,
        "endAt": 1662011999000
      }
    ],
    "virtualShopType": "birthday"
  },
  {
    "id": 62,
    "name": "에무 BIRTHDAY",
    "virtualShopItems": [
      {
        "id": 123,
        "virtualShopId": 62,
        "virtualShopItemType": "coordinate",
        "seq": 99967,
        "resourceBoxId": 123,
        "costPaidJewel": 1000,
        "startAt": 1662530400000,
        "endAt": 1662789599000
      }
    ],
    "virtualShopType": "birthday"
  }
]